<annotation>
	<folder>images</folder>
	<filename>zanzibar1_209.jpg</filename>
	<path>C:\Users\bcham\Documents\Tensorflow\workspace\Zanzibar\images\zanzibar1_209.jpg</path>
	<source>
		<database>Unknown</database>
	</source>
	<size>
		<width>1000</width>
		<height>1000</height>
		<depth>3</depth>
	</size>
	<segmented>0</segmented>
	<object>
		<name>Palm</name>
		<pose>Unspecified</pose>
		<truncated>0</truncated>
		<difficult>0</difficult>
		<bndbox>
			<xmin>660</xmin>
			<ymin>73</ymin>
			<xmax>735</xmax>
			<ymax>159</ymax>
		</bndbox>
	</object>
	<object>
		<name>Palm</name>
		<pose>Unspecified</pose>
		<truncated>0</truncated>
		<difficult>0</difficult>
		<bndbox>
			<xmin>9</xmin>
			<ymin>674</ymin>
			<xmax>98</xmax>
			<ymax>775</ymax>
		</bndbox>
	</object>
	<object>
		<name>Palm</name>
		<pose>Unspecified</pose>
		<truncated>0</truncated>
		<difficult>0</difficult>
		<bndbox>
			<xmin>79</xmin>
			<ymin>664</ymin>
			<xmax>170</xmax>
			<ymax>750</ymax>
		</bndbox>
	</object>
	<object>
		<name>Palm</name>
		<pose>Unspecified</pose>
		<truncated>0</truncated>
		<difficult>0</difficult>
		<bndbox>
			<xmin>170</xmin>
			<ymin>662</ymin>
			<xmax>277</xmax>
			<ymax>760</ymax>
		</bndbox>
	</object>
	<object>
		<name>Palm</name>
		<pose>Unspecified</pose>
		<truncated>0</truncated>
		<difficult>0</difficult>
		<bndbox>
			<xmin>62</xmin>
			<ymin>826</ymin>
			<xmax>151</xmax>
			<ymax>911</ymax>
		</bndbox>
	</object>
	<object>
		<name>Palm</name>
		<pose>Unspecified</pose>
		<truncated>0</truncated>
		<difficult>0</difficult>
		<bndbox>
			<xmin>233</xmin>
			<ymin>780</ymin>
			<xmax>341</xmax>
			<ymax>890</ymax>
		</bndbox>
	</object>
	<object>
		<name>Palm</name>
		<pose>Unspecified</pose>
		<truncated>0</truncated>
		<difficult>0</difficult>
		<bndbox>
			<xmin>325</xmin>
			<ymin>868</ymin>
			<xmax>413</xmax>
			<ymax>949</ymax>
		</bndbox>
	</object>
	<object>
		<name>Palm</name>
		<pose>Unspecified</pose>
		<truncated>0</truncated>
		<difficult>0</difficult>
		<bndbox>
			<xmin>447</xmin>
			<ymin>802</ymin>
			<xmax>549</xmax>
			<ymax>896</ymax>
		</bndbox>
	</object>
	<object>
		<name>Palm</name>
		<pose>Unspecified</pose>
		<truncated>0</truncated>
		<difficult>0</difficult>
		<bndbox>
			<xmin>451</xmin>
			<ymin>676</ymin>
			<xmax>540</xmax>
			<ymax>767</ymax>
		</bndbox>
	</object>
	<object>
		<name>Palm</name>
		<pose>Unspecified</pose>
		<truncated>0</truncated>
		<difficult>0</difficult>
		<bndbox>
			<xmin>546</xmin>
			<ymin>580</ymin>
			<xmax>635</xmax>
			<ymax>664</ymax>
		</bndbox>
	</object>
	<object>
		<name>Palm</name>
		<pose>Unspecified</pose>
		<truncated>0</truncated>
		<difficult>0</difficult>
		<bndbox>
			<xmin>527</xmin>
			<ymin>652</ymin>
			<xmax>620</xmax>
			<ymax>739</ymax>
		</bndbox>
	</object>
	<object>
		<name>Palm</name>
		<pose>Unspecified</pose>
		<truncated>0</truncated>
		<difficult>0</difficult>
		<bndbox>
			<xmin>604</xmin>
			<ymin>806</ymin>
			<xmax>701</xmax>
			<ymax>901</ymax>
		</bndbox>
	</object>
	<object>
		<name>Palm</name>
		<pose>Unspecified</pose>
		<truncated>0</truncated>
		<difficult>0</difficult>
		<bndbox>
			<xmin>676</xmin>
			<ymin>610</ymin>
			<xmax>777</xmax>
			<ymax>707</ymax>
		</bndbox>
	</object>
	<object>
		<name>Palm</name>
		<pose>Unspecified</pose>
		<truncated>0</truncated>
		<difficult>0</difficult>
		<bndbox>
			<xmin>791</xmin>
			<ymin>593</ymin>
			<xmax>897</xmax>
			<ymax>693</ymax>
		</bndbox>
	</object>
	<object>
		<name>Palm</name>
		<pose>Unspecified</pose>
		<truncated>0</truncated>
		<difficult>0</difficult>
		<bndbox>
			<xmin>912</xmin>
			<ymin>551</ymin>
			<xmax>999</xmax>
			<ymax>650</ymax>
		</bndbox>
	</object>
	<object>
		<name>Palm</name>
		<pose>Unspecified</pose>
		<truncated>0</truncated>
		<difficult>0</difficult>
		<bndbox>
			<xmin>891</xmin>
			<ymin>729</ymin>
			<xmax>985</xmax>
			<ymax>823</ymax>
		</bndbox>
	</object>
	<object>
		<name>Palm</name>
		<pose>Unspecified</pose>
		<truncated>0</truncated>
		<difficult>0</difficult>
		<bndbox>
			<xmin>691</xmin>
			<ymin>736</ymin>
			<xmax>784</xmax>
			<ymax>825</ymax>
		</bndbox>
	</object>
	<object>
		<name>Palm</name>
		<pose>Unspecified</pose>
		<truncated>0</truncated>
		<difficult>0</difficult>
		<bndbox>
			<xmin>754</xmin>
			<ymin>838</ymin>
			<xmax>848</xmax>
			<ymax>925</ymax>
		</bndbox>
	</object>
</annotation>
