<annotation>
	<folder>images</folder>
	<filename>zanzibar2_1105.jpg</filename>
	<path>C:\Users\bcham\Documents\Tensorflow\workspace\Zanzibar\images\zanzibar2_1105.jpg</path>
	<source>
		<database>Unknown</database>
	</source>
	<size>
		<width>1000</width>
		<height>1000</height>
		<depth>3</depth>
	</size>
	<segmented>0</segmented>
	<object>
		<name>Palm</name>
		<pose>Unspecified</pose>
		<truncated>1</truncated>
		<difficult>0</difficult>
		<bndbox>
			<xmin>18</xmin>
			<ymin>1</ymin>
			<xmax>140</xmax>
			<ymax>97</ymax>
		</bndbox>
	</object>
	<object>
		<name>Palm</name>
		<pose>Unspecified</pose>
		<truncated>0</truncated>
		<difficult>0</difficult>
		<bndbox>
			<xmin>242</xmin>
			<ymin>4</ymin>
			<xmax>355</xmax>
			<ymax>116</ymax>
		</bndbox>
	</object>
	<object>
		<name>Palm</name>
		<pose>Unspecified</pose>
		<truncated>0</truncated>
		<difficult>0</difficult>
		<bndbox>
			<xmin>251</xmin>
			<ymin>202</ymin>
			<xmax>381</xmax>
			<ymax>329</ymax>
		</bndbox>
	</object>
	<object>
		<name>Palm</name>
		<pose>Unspecified</pose>
		<truncated>0</truncated>
		<difficult>0</difficult>
		<bndbox>
			<xmin>405</xmin>
			<ymin>293</ymin>
			<xmax>498</xmax>
			<ymax>389</ymax>
		</bndbox>
	</object>
	<object>
		<name>Palm</name>
		<pose>Unspecified</pose>
		<truncated>0</truncated>
		<difficult>0</difficult>
		<bndbox>
			<xmin>18</xmin>
			<ymin>610</ymin>
			<xmax>135</xmax>
			<ymax>746</ymax>
		</bndbox>
	</object>
	<object>
		<name>Palm</name>
		<pose>Unspecified</pose>
		<truncated>0</truncated>
		<difficult>0</difficult>
		<bndbox>
			<xmin>695</xmin>
			<ymin>566</ymin>
			<xmax>812</xmax>
			<ymax>672</ymax>
		</bndbox>
	</object>
	<object>
		<name>Palm</name>
		<pose>Unspecified</pose>
		<truncated>0</truncated>
		<difficult>0</difficult>
		<bndbox>
			<xmin>345</xmin>
			<ymin>816</ymin>
			<xmax>455</xmax>
			<ymax>916</ymax>
		</bndbox>
	</object>
	<object>
		<name>Palm</name>
		<pose>Unspecified</pose>
		<truncated>0</truncated>
		<difficult>0</difficult>
		<bndbox>
			<xmin>892</xmin>
			<ymin>776</ymin>
			<xmax>996</xmax>
			<ymax>873</ymax>
		</bndbox>
	</object>
	<object>
		<name>Palm</name>
		<pose>Unspecified</pose>
		<truncated>1</truncated>
		<difficult>0</difficult>
		<bndbox>
			<xmin>907</xmin>
			<ymin>692</ymin>
			<xmax>1000</xmax>
			<ymax>783</ymax>
		</bndbox>
	</object>
</annotation>
